odoo/addons/web_widget_mpld3_chart/README.rst
odoo/addons/web_widget_mpld3_chart/__init__.py
odoo/addons/web_widget_mpld3_chart/__manifest__.py
odoo/addons/web_widget_mpld3_chart/i18n/es.po
odoo/addons/web_widget_mpld3_chart/i18n/it.po
odoo/addons/web_widget_mpld3_chart/i18n/web_widget_mpld3_chart.pot
odoo/addons/web_widget_mpld3_chart/models/__init__.py
odoo/addons/web_widget_mpld3_chart/models/abstract_mpld3_parser.py
odoo/addons/web_widget_mpld3_chart/readme/CONTRIBUTORS.md
odoo/addons/web_widget_mpld3_chart/readme/CREDITS.md
odoo/addons/web_widget_mpld3_chart/readme/DESCRIPTION.md
odoo/addons/web_widget_mpld3_chart/readme/INSTALL.md
odoo/addons/web_widget_mpld3_chart/readme/USAGE.md
odoo/addons/web_widget_mpld3_chart/static/description/icon.png
odoo/addons/web_widget_mpld3_chart/static/description/index.html
odoo/addons/web_widget_mpld3_chart/static/src/js/web_widget_mpld3_chart.esm.js
odoo/addons/web_widget_mpld3_chart/static/src/lib/d3/d3.v5.js
odoo/addons/web_widget_mpld3_chart/static/src/lib/mpld3/mpld3.v0.5.10.js
odoo/addons/web_widget_mpld3_chart/static/src/xml/web_widget_mpld3_chart.xml
odoo_addon_web_widget_mpld3_chart-18.0.1.0.0.2.dist-info/METADATA
odoo_addon_web_widget_mpld3_chart-18.0.1.0.0.2.dist-info/WHEEL
odoo_addon_web_widget_mpld3_chart-18.0.1.0.0.2.dist-info/top_level.txt
odoo_addon_web_widget_mpld3_chart-18.0.1.0.0.2.dist-info/RECORD
